{
  "lastTopic": "test-topic",
  "history": [
    {
      "topic": "tìm source backend",
      "timestamp": "2026-06-03T05:08:41.039Z"
    },
    {
      "topic": "test-topic",
      "timestamp": "2026-06-05T07:59:21.274Z"
    },
    {
      "topic": "test-topic",
      "timestamp": "2026-06-05T09:29:37.363Z"
    },
    {
      "topic": "test-topic",
      "timestamp": "2026-06-05T09:47:53.968Z"
    },
    {
      "topic": "test-topic",
      "timestamp": "2026-06-05T10:16:19.575Z"
    },
    {
      "topic": "test-topic",
      "timestamp": "2026-06-06T18:11:31.659Z"
    },
    {
      "topic": "test-topic",
      "timestamp": "2026-06-06T18:19:44.650Z"
    },
    {
      "topic": "test-topic",
      "timestamp": "2026-06-06T20:31:33.115Z"
    },
    {
      "topic": "test-topic",
      "timestamp": "2026-06-06T22:48:16.062Z"
    },
    {
      "topic": "test-topic",
      "timestamp": "2026-06-06T23:13:17.790Z"
    },
    {
      "topic": "test-topic",
      "timestamp": "2026-06-06T23:22:22.879Z"
    },
    {
      "topic": "test-topic",
      "timestamp": "2026-06-06T23:24:39.134Z"
    },
    {
      "topic": "test-topic",
      "timestamp": "2026-06-06T23:54:27.268Z"
    },
    {
      "topic": "test-topic",
      "timestamp": "2026-06-07T00:10:30.275Z"
    },
    {
      "topic": "test-topic",
      "timestamp": "2026-06-07T04:44:39.832Z"
    },
    {
      "topic": "test-topic",
      "timestamp": "2026-06-08T01:21:05.815Z"
    },
    {
      "topic": "test-topic",
      "timestamp": "2026-06-09T04:06:27.215Z"
    },
    {
      "topic": "test-topic",
      "timestamp": "2026-06-09T06:43:56.556Z"
    },
    {
      "topic": "test-topic",
      "timestamp": "2026-06-09T06:48:53.017Z"
    },
    {
      "topic": "test-topic",
      "timestamp": "2026-06-09T06:57:40.587Z"
    },
    {
      "topic": "test-topic",
      "timestamp": "2026-06-09T07:03:44.142Z"
    },
    {
      "topic": "test-topic",
      "timestamp": "2026-06-09T07:07:20.759Z"
    },
    {
      "topic": "test-topic",
      "timestamp": "2026-06-09T07:09:46.751Z"
    },
    {
      "topic": "test-topic",
      "timestamp": "2026-06-09T07:34:20.893Z"
    },
    {
      "topic": "test-topic",
      "timestamp": "2026-06-11T00:35:29.489Z"
    },
    {
      "topic": "test-topic",
      "timestamp": "2026-06-11T00:36:54.140Z"
    },
    {
      "topic": "test-topic",
      "timestamp": "2026-06-11T00:38:37.473Z"
    },
    {
      "topic": "test-topic",
      "timestamp": "2026-06-11T02:54:53.183Z"
    },
    {
      "topic": "test-topic",
      "timestamp": "2026-06-11T02:56:00.677Z"
    },
    {
      "topic": "test-topic",
      "timestamp": "2026-06-11T02:56:52.911Z"
    },
    {
      "topic": "test-topic",
      "timestamp": "2026-06-11T02:57:45.385Z"
    },
    {
      "topic": "test-topic",
      "timestamp": "2026-06-11T02:59:05.328Z"
    },
    {
      "topic": "test-topic",
      "timestamp": "2026-06-11T03:10:02.614Z"
    },
    {
      "topic": "test-topic",
      "timestamp": "2026-06-11T04:40:37.053Z"
    },
    {
      "topic": "test-topic",
      "timestamp": "2026-06-11T05:30:39.836Z"
    },
    {
      "topic": "test-topic",
      "timestamp": "2026-06-11T05:36:46.810Z"
    },
    {
      "topic": "test-topic",
      "timestamp": "2026-06-12T00:47:29.381Z"
    },
    {
      "topic": "test-topic",
      "timestamp": "2026-06-12T00:58:54.013Z"
    },
    {
      "topic": "test-topic",
      "timestamp": "2026-06-12T05:05:05.831Z"
    },
    {
      "topic": "test-topic",
      "timestamp": "2026-06-12T05:18:00.604Z"
    },
    {
      "topic": "test-topic",
      "timestamp": "2026-06-12T05:19:42.832Z"
    },
    {
      "topic": "test-topic",
      "timestamp": "2026-06-12T05:21:15.365Z"
    },
    {
      "topic": "test-topic",
      "timestamp": "2026-06-12T05:22:04.698Z"
    },
    {
      "topic": "test-topic",
      "timestamp": "2026-06-12T05:23:06.461Z"
    },
    {
      "topic": "test-topic",
      "timestamp": "2026-06-12T05:25:16.525Z"
    },
    {
      "topic": "test-topic",
      "timestamp": "2026-06-12T06:04:56.341Z"
    },
    {
      "topic": "test-topic",
      "timestamp": "2026-06-12T20:43:51.565Z"
    },
    {
      "topic": "test-topic",
      "timestamp": "2026-06-12T20:48:51.729Z"
    },
    {
      "topic": "test-topic",
      "timestamp": "2026-06-12T20:57:56.064Z"
    },
    {
      "topic": "test-topic",
      "timestamp": "2026-06-12T21:18:19.629Z"
    },
    {
      "topic": "test-topic",
      "timestamp": "2026-06-12T22:18:08.408Z"
    },
    {
      "topic": "test-topic",
      "timestamp": "2026-06-13T03:02:20.151Z"
    },
    {
      "topic": "test-topic",
      "timestamp": "2026-06-13T03:34:29.032Z"
    },
    {
      "topic": "test-topic",
      "timestamp": "2026-06-13T05:24:33.825Z"
    },
    {
      "topic": "test-topic",
      "timestamp": "2026-06-13T05:44:30.994Z"
    },
    {
      "topic": "test-topic",
      "timestamp": "2026-06-13T06:20:17.099Z"
    },
    {
      "topic": "test-topic",
      "timestamp": "2026-06-13T18:27:30.415Z"
    },
    {
      "topic": "test-topic",
      "timestamp": "2026-06-13T18:37:41.518Z"
    },
    {
      "topic": "test-topic",
      "timestamp": "2026-06-13T18:57:36.928Z"
    },
    {
      "topic": "test-topic",
      "timestamp": "2026-06-13T19:10:37.698Z"
    },
    {
      "topic": "test-topic",
      "timestamp": "2026-06-13T19:43:57.068Z"
    },
    {
      "topic": "test-topic",
      "timestamp": "2026-06-13T19:48:12.244Z"
    },
    {
      "topic": "test-topic",
      "timestamp": "2026-06-13T19:51:55.755Z"
    },
    {
      "topic": "test-topic",
      "timestamp": "2026-06-14T06:13:25.042Z"
    },
    {
      "topic": "test-topic",
      "timestamp": "2026-06-14T06:18:51.645Z"
    },
    {
      "topic": "test-topic",
      "timestamp": "2026-06-14T06:25:33.923Z"
    },
    {
      "topic": "test-topic",
      "timestamp": "2026-06-14T06:27:25.498Z"
    },
    {
      "topic": "test-topic",
      "timestamp": "2026-06-14T06:32:59.191Z"
    },
    {
      "topic": "test-topic",
      "timestamp": "2026-06-14T06:35:45.514Z"
    },
    {
      "topic": "test-topic",
      "timestamp": "2026-06-14T06:59:24.734Z"
    },
    {
      "topic": "test-topic",
      "timestamp": "2026-06-14T07:05:32.420Z"
    },
    {
      "topic": "test-topic",
      "timestamp": "2026-06-14T07:06:15.908Z"
    },
    {
      "topic": "test-topic",
      "timestamp": "2026-06-14T07:09:36.754Z"
    },
    {
      "topic": "test-topic",
      "timestamp": "2026-06-14T07:12:45.725Z"
    },
    {
      "topic": "test-topic",
      "timestamp": "2026-06-14T07:14:57.118Z"
    },
    {
      "topic": "test-topic",
      "timestamp": "2026-06-14T07:18:17.474Z"
    },
    {
      "topic": "test-topic",
      "timestamp": "2026-06-14T07:43:21.371Z"
    },
    {
      "topic": "test-topic",
      "timestamp": "2026-06-14T07:58:56.327Z"
    },
    {
      "topic": "test-topic",
      "timestamp": "2026-06-14T09:09:35.758Z"
    },
    {
      "topic": "test-topic",
      "timestamp": "2026-06-14T09:59:49.673Z"
    },
    {
      "topic": "test-topic",
      "timestamp": "2026-06-14T10:10:32.764Z"
    }
  ],
  "transitionCounts": {
    "tìm source backend": {
      "test-topic": 1
    },
    "test-topic": {
      "test-topic": 79
    }
  },
  "interests": [
    "test-topic"
  ],
  "interestCounts": {
    "test-topic": 13
  }
}